banxicoapi/__init__.py
banxicoapi/banxico_api.py
tests/__init__.py
tests/banxico_test.py
tests/conftest.py
banxicoapi-1.0.2.dist-info/LICENSE
banxicoapi-1.0.2.dist-info/METADATA
banxicoapi-1.0.2.dist-info/WHEEL
banxicoapi-1.0.2.dist-info/top_level.txt
banxicoapi-1.0.2.dist-info/RECORD
