Metadata-Version: 2.1
Name: banxicoapi
Version: 1.0.2
Summary: Client for Banxico API
Home-page: https://github.com/EliasManj/banxico-api
Author: Elias Manjarrez
Author-email: miguel.elias.g.manjarrez@gnail.com
Classifier: Programming Language :: Python :: 3
Classifier: License :: OSI Approved :: MIT License
Classifier: Operating System :: OS Independent
Requires-Python: >=3.6
License-File: LICENSE
Requires-Dist: requests
Requires-Dist: pyyaml
